{
    "dynamicInfo": [
        {
            "replacingName": "#selfMaintenanceHistory#",
            "content": {
                "lastSelfCleanDate": "11/02/2023",
                "lastPumpFilterCleanDate": "07/20/2023"
            }
        },
        {
            "replacingName": "#cycleHistory#",
            "content":{
                "Normal":"03/14/2024",
                "Jeans":"03/14/2024",
                "DrainAndSpin":"03/14/2024",
                "Delicates":"03/18/2024"
            }
        }
    ]
}
